[
    {
        "code": "GRL",
        "value": -25
    },
    {
        "code": "CAN",
        "value": -8
    },
    {
        "code": "RUS",
        "value": -12
    },
    {
        "code": "MNG",
        "value": -2
    },
    {
        "code": "ISL",
        "value": 5
    },
    {
        "code": "NOR",
        "value": 3
    },
    {
        "code": "FIN",
        "value": 1
    },
    {
        "code": "SWE",
        "value": 5
    },
    {
        "code": "KGZ",
        "value": 12
    },
    {
        "code": "TJK",
        "value": 15
    },
    {
        "code": "EST",
        "value": 6
    },
    {
        "code": "FRO",
        "value": 7
    },
    {
        "code": "LVA",
        "value": 7
    },
    {
        "code": "PRK",
        "value": 4
    },
    {
        "code": "LTU",
        "value": 8
    },
    {
        "code": "BLR",
        "value": 5
    },
    {
        "code": "KAZ",
        "value": 2
    },
    {
        "code": "CHE",
        "value": 22
    },
    {
        "code": "CHN",
        "value": 18
    },
    {
        "code": "ARM",
        "value": 25
    },
    {
        "code": "AUT",
        "value": 20
    },
    {
        "code": "LIE",
        "value": 21
    },
    {
        "code": "CHL",
        "value": 26
    },
    {
        "code": "POL",
        "value": 12
    },
    {
        "code": "CZE",
        "value": 14
    },
    {
        "code": "USA",
        "value": 23
    },
    {
        "code": "AND",
        "value": 24
    },
    {
        "code": "DNK",
        "value": 13
    },
    {
        "code": "SVK",
        "value": 15
    },
    {
        "code": "GEO",
        "value": 26
    },
    {
        "code": "UKR",
        "value": 11
    },
    {
        "code": "GBR",
        "value": 18
    },
    {
        "code": "IRL",
        "value": 19
    },
    {
        "code": "BTN",
        "value": 29
    },
    {
        "code": "DEU",
        "value": 16
    },
    {
        "code": "MNE",
        "value": 23
    },
    {
        "code": "SVN",
        "value": 21
    },
    {
        "code": "ROU",
        "value": 13
    },
    {
        "code": "LUX",
        "value": 17
    },
    {
        "code": "BIH",
        "value": 22
    },
    {
        "code": "NZL",
        "value": 23
    },
    {
        "code": "MKD",
        "value": 24
    },
    {
        "code": "NLD",
        "value": 15
    },
    {
        "code": "MDA",
        "value": 12
    },
    {
        "code": "BEL",
        "value": 16
    },
    {
        "code": "TUR",
        "value": 28
    },
    {
        "code": "BGR",
        "value": 20
    },
    {
        "code": "JPN",
        "value": 25
    },
    {
        "code": "SRB",
        "value": 21
    },
    {
        "code": "HUN",
        "value": 18
    },
    {
        "code": "LSO",
        "value": 22
    },
    {
        "code": "KOR",
        "value": 14
    },
    {
        "code": "FRA",
        "value": 20
    },
    {
        "code": "HRV",
        "value": 22
    },
    {
        "code": "ALB",
        "value": 26
    },
    {
        "code": "AZE",
        "value": 24
    },
    {
        "code": "SMR",
        "value": 27
    },
    {
        "code": "ITA",
        "value": 27
    },
    {
        "code": "NPL",
        "value": 32
    },
    {
        "code": "AFG",
        "value": 21
    },
    {
        "code": "UZB",
        "value": 23
    },
    {
        "code": "GRC",
        "value": 30
    },
    {
        "code": "MCO",
        "value": 29
    },
    {
        "code": "ARG",
        "value": 28
    },
    {
        "code": "ESP",
        "value": 28
    },
    {
        "code": "LBN",
        "value": 33
    },
    {
        "code": "PRT",
        "value": 26
    },
    {
        "code": "TKM",
        "value": 25
    },
    {
        "code": "URY",
        "value": 29
    },
    {
        "code": "ZAF",
        "value": 27
    },
    {
        "code": "MAR",
        "value": 31
    },
    {
        "code": "RWA",
        "value": 26
    },
    {
        "code": "SYR",
        "value": 30
    },
    {
        "code": "IRN",
        "value": 27
    },
    {
        "code": "CYP",
        "value": 32
    },
    {
        "code": "PER",
        "value": 26
    },
    {
        "code": "PSE",
        "value": 32
    },
    {
        "code": "JOR",
        "value": 31
    },
    {
        "code": "ISR",
        "value": 34
    },
    {
        "code": "NAM",
        "value": 29
    },
    {
        "code": "MLT",
        "value": 31
    },
    {
        "code": "BDI",
        "value": 27
    },
    {
        "code": "BOL",
        "value": 24
    },
    {
        "code": "TWN",
        "value": 33
    },
    {
        "code": "SWZ",
        "value": 28
    },
    {
        "code": "ECU",
        "value": 23
    },
    {
        "code": "TUN",
        "value": 29
    },
    {
        "code": "AGO",
        "value": 29
    },
    {
        "code": "MEX",
        "value": 34
    },
    {
        "code": "ZWE",
        "value": 27
    },
    {
        "code": "ZMB",
        "value": 28
    },
    {
        "code": "AUS",
        "value": 29
    },
    {
        "code": "BWA",
        "value": 29
    },
    {
        "code": "PAK",
        "value": 30
    },
    {
        "code": "MWI",
        "value": 28
    },
    {
        "code": "CPV",
        "value": 26
    },
    {
        "code": "MDG",
        "value": 29
    },
    {
        "code": "LBY",
        "value": 32
    },
    {
        "code": "TZA",
        "value": 28
    },
    {
        "code": "UGA",
        "value": 28
    },
    {
        "code": "EGY",
        "value": 34
    },
    {
        "code": "MUS",
        "value": 29
    },
    {
        "code": "NCL",
        "value": 29
    },
    {
        "code": "MAC",
        "value": 34
    },
    {
        "code": "ETH",
        "value": 26
    },
    {
        "code": "HKG",
        "value": 35
    },
    {
        "code": "COM",
        "value": 29
    },
    {
        "code": "GTM",
        "value": 24
    },
    {
        "code": "IRQ",
        "value": 31
    },
    {
        "code": "PRY",
        "value": 29
    },
    {
        "code": "MMR",
        "value": 27
    },
    {
        "code": "LAO",
        "value": 25
    },
    {
        "code": "PYF",
        "value": 29
    },
    {
        "code": "DZA",
        "value": 30
    },
    {
        "code": "COG",
        "value": 29
    },
    {
        "code": "MOZ",
        "value": 29
    },
    {
        "code": "DOM",
        "value": 27
    },
    {
        "code": "CRI",
        "value": 26
    },
    {
        "code": "STP",
        "value": 29
    },
    {
        "code": "HND",
        "value": 27
    },
    {
        "code": "COL",
        "value": 23
    },
    {
        "code": "VNM",
        "value": 24
    },
    {
        "code": "VUT",
        "value": 29
    },
    {
        "code": "PNG",
        "value": 29
    },
    {
        "code": "MYT",
        "value": 29
    },
    {
        "code": "GNQ",
        "value": 29
    },
    {
        "code": "PRI",
        "value": 27
    },
    {
        "code": "CMR",
        "value": 27
    },
    {
        "code": "FJI",
        "value": 29
    },
    {
        "code": "HTI",
        "value": 27
    },
    {
        "code": "TON",
        "value": 29
    },
    {
        "code": "IND",
        "value": 31
    },
    {
        "code": "KEN",
        "value": 28
    },
    {
        "code": "SLV",
        "value": 27
    },
    {
        "code": "PAN",
        "value": 27
    },
    {
        "code": "GAB",
        "value": 29
    },
    {
        "code": "LBR",
        "value": 29
    },
    {
        "code": "YEM",
        "value": 27
    },
    {
        "code": "VEN",
        "value": 29
    },
    {
        "code": "BRA",
        "value": 27
    },
    {
        "code": "CAF",
        "value": 27
    },
    {
        "code": "BGD",
        "value": 32
    },
    {
        "code": "NIC",
        "value": 27
    },
    {
        "code": "BLZ",
        "value": 27
    },
    {
        "code": "SLB",
        "value": 29
    },
    {
        "code": "GIN",
        "value": 29
    },
    {
        "code": "IDN",
        "value": 29
    },
    {
        "code": "VCT",
        "value": 29
    },
    {
        "code": "JAM",
        "value": 27
    },
    {
        "code": "BHS",
        "value": 26
    },
    {
        "code": "CUB",
        "value": 26
    },
    {
        "code": "GUY",
        "value": 29
    },
    {
        "code": "GRD",
        "value": 29
    },
    {
        "code": "MYS",
        "value": 29
    },
    {
        "code": "BRB",
        "value": 29
    },
    {
        "code": "TTO",
        "value": 29
    },
    {
        "code": "SAU",
        "value": 33
    },
    {
        "code": "ERI",
        "value": 27
    },
    {
        "code": "SUR",
        "value": 29
    },
    {
        "code": "PHL",
        "value": 29
    },
    {
        "code": "SLE",
        "value": 29
    },
    {
        "code": "DMA",
        "value": 29
    },
    {
        "code": "THA",
        "value": 27
    },
    {
        "code": "LCA",
        "value": 29
    },
    {
        "code": "VGB",
        "value": 27
    },
    {
        "code": "CIV",
        "value": 29
    },
    {
        "code": "ATG",
        "value": 29
    },
    {
        "code": "SOM",
        "value": 29
    },
    {
        "code": "SYC",
        "value": 29
    },
    {
        "code": "NGA",
        "value": 29
    },
    {
        "code": "LKA",
        "value": 29
    },
    {
        "code": "MNP",
        "value": 27
    },
    {
        "code": "KHM",
        "value": 29
    },
    {
        "code": "TCD",
        "value": 34
    },
    {
        "code": "ASM",
        "value": 29
    },
    {
        "code": "KNA",
        "value": 29
    },
    {
        "code": "FSM",
        "value": 29
    },
    {
        "code": "TGO",
        "value": 29
    },
    {
        "code": "WSM",
        "value": 29
    },
    {
        "code": "PLW",
        "value": 29
    },
    {
        "code": "GUM",
        "value": 29
    },
    {
        "code": "SDN",
        "value": 36
    },
    {
        "code": "KWT",
        "value": 31
    },
    {
        "code": "NER",
        "value": 35
    },
    {
        "code": "SGP",
        "value": 29
    },
    {
        "code": "GHA",
        "value": 29
    },
    {
        "code": "KIR",
        "value": 29
    },
    {
        "code": "MHL",
        "value": 29
    },
    {
        "code": "OMN",
        "value": 34
    },
    {
        "code": "CYM",
        "value": 26
    },
    {
        "code": "GNB",
        "value": 29
    },
    {
        "code": "MDV",
        "value": 29
    },
    {
        "code": "BEN",
        "value": 29
    },
    {
        "code": "GMB",
        "value": 27
    },
    {
        "code": "DJI",
        "value": 29
    },
    {
        "code": "ABW",
        "value": 29
    },
    {
        "code": "BHR",
        "value": 33
    },
    {
        "code": "MRT",
        "value": 34
    },
    {
        "code": "ARE",
        "value": 35
    },
    {
        "code": "SEN",
        "value": 27
    },
    {
        "code": "QAT",
        "value": 35
    },
    {
        "code": "MLI",
        "value": 36
    },
    {
        "code": "BFA",
        "value": 35
    },
    {
        "code": "TLS",
        "value": 29
    },
    {
        "code": "BRN",
        "value": 29
    },
    {
        "code": "NRU",
        "value": 29
    },
    {
        "code": "TUV",
        "value": 29
    },
    {
        "code": "SSD",
        "value": 36
    },
    {
        "code": "VAT",
        "value": 27
    },
    {
        "code": "COD",
        "value": 27
    },
    {
        "code": "XKX",
        "value": 22
    },
    {
        "code": "AIA",
        "value": 29
    },
    {
        "code": "TCA",
        "value": 27
    }
]